{
  "HT_Text_BOS_Tab_Artifacts": {
    "message": "Manufatti "
  },
  "HT_Text_BOS_Tab_Notes": {
    "message": "Note"
  },
  "HT_Text_BOS_Tab_Monsters": {
    "message": "Mostri"
  },
  "HT_Text_BOS_Instructions": {
    "message": "<FC 30,10,0>Muoviti fra le pagine usando <SB HT_PadAction_BOS_NavigateDPad> <N>Cambia pagine usando <SB HT_PadAction_BOS_TABCycleLeft> e <SB HT_PadAction_BOS_TABCycleRight><N>Fai scorrere le descrizioni lunghe con <SB HT_PadAction_BOS_PageUp>."
  },
  "HT_Text_BOS_NoNotes": {
    "message": "<ES HT_Text_ES_S_BOSStd>Attualmente non ci sono note.<ES HT_Text_ES_E_BOSStd>"
  },
  "HT_Text_BOS_NoAbilities": {
    "message": "<ES HT_Text_ES_S_BOSStd>Attualmente non possiedi alcuna abilità.<ES HT_Text_ES_E_BOSStd>"
  },
  "HT_Text_BOS_NoQuestItems": {
    "message": "<ES HT_Text_ES_S_BOSStd>Al momento non hai alcun oggetto missione.<ES HT_Text_ES_E_BOSStd>"
  }
}